autoclasswrapper/__init__.py
autoclasswrapper/input.py
autoclasswrapper/output.py
autoclasswrapper/run.py
autoclasswrapper/tools.py
autoclasswrapper-1.5.1.dist-info/LICENSE.txt
autoclasswrapper-1.5.1.dist-info/METADATA
autoclasswrapper-1.5.1.dist-info/WHEEL
autoclasswrapper-1.5.1.dist-info/top_level.txt
autoclasswrapper-1.5.1.dist-info/RECORD
