Metadata-Version: 2.1
Name: autoclasswrapper
Version: 1.5.1
Summary: AutoClassWrapper: a Python wrapper for AutoClass C classification.
Home-page: https://github.com/pierrepo/autoclasswrapper
Author: Pierre Poulain
Author-email: pierre.poulain@cupnet.net
License: BSD 3-Clause License
Keywords: autoclass,clustering,proteins,genes
Platform: UNKNOWN
Classifier: Development Status :: 5 - Production/Stable
Classifier: Intended Audience :: Science/Research
Classifier: Intended Audience :: Developers
Classifier: Topic :: Scientific/Engineering
Classifier: Topic :: Scientific/Engineering :: Bio-Informatics
Classifier: Natural Language :: English
Classifier: License :: OSI Approved :: BSD License
Classifier: Programming Language :: Python
Classifier: Programming Language :: Python :: 3
Classifier: Programming Language :: Python :: 3.4
Classifier: Programming Language :: Python :: 3.5
Classifier: Programming Language :: Python :: 3.6
Requires-Python: >=3.4
Requires-Dist: numpy
Requires-Dist: pandas
Requires-Dist: scipy
Requires-Dist: matplotlib
Requires-Dist: chardet
